flask_parcel.py
Flask_Parcel-0.0.3.dist-info/LICENSE
Flask_Parcel-0.0.3.dist-info/METADATA
Flask_Parcel-0.0.3.dist-info/WHEEL
Flask_Parcel-0.0.3.dist-info/top_level.txt
Flask_Parcel-0.0.3.dist-info/RECORD
