Metadata-Version: 2.1
Name: Flask-Parcel
Version: 0.0.3
Summary: Run parcel builds alongside flask.
Home-page: https://github.com/ysenarath/flask-parcel
Author: Yasas Senarath
Author-email: ysenarath.93@gmail.com
License: MIT
Platform: any
Classifier: Environment :: Web Environment
Classifier: Intended Audience :: Developers
Classifier: License :: OSI Approved :: MIT License
Classifier: Operating System :: OS Independent
Classifier: Programming Language :: Python
Classifier: Topic :: Internet :: WWW/HTTP :: Dynamic Content
Classifier: Topic :: Software Development :: Libraries :: Python Modules
License-File: LICENSE
Requires-Dist: Flask
